dnadiffusion/__about__.py
dnadiffusion/__init__.py
dnadiffusion/__main__.py
dnadiffusion/cli/__init__.py
dnadiffusion/data/__init__.py
dnadiffusion/data/dataloader.py
dnadiffusion/models/__init__.py
dnadiffusion/models/diffusion.py
dnadiffusion/models/layers.py
dnadiffusion/models/pretrained_unet.py
dnadiffusion/models/unet.py
dnadiffusion/utils/__init__.py
dnadiffusion/utils/sample_util.py
dnadiffusion/utils/train_util.py
dnadiffusion/utils/utils.py
dnadiffusion-0.1.1.dist-info/METADATA
dnadiffusion-0.1.1.dist-info/WHEEL
dnadiffusion-0.1.1.dist-info/entry_points.txt
dnadiffusion-0.1.1.dist-info/licenses/LICENSE.md
dnadiffusion-0.1.1.dist-info/RECORD
