Metadata-Version: 2.4
Name: dnadiffusion
Version: 0.1.1
Summary: Library for generation of synthetic regulatory elements using diffusion models
Project-URL: Documentation, https://pinellolab.github.io/DNA-Diffusion
Project-URL: Source, https://github.com/pinellolab/DNA-Diffusion
Author-email: dnadiffusion <dnadiffusion@pinellolab.org>
License-File: LICENSE.md
Classifier: Programming Language :: Python :: 3 :: Only
Requires-Python: >=3.12
Requires-Dist: einops>=0.8.1
Requires-Dist: hydra-core>=1.3.2
Requires-Dist: jupyterlab>=4.4.0
Requires-Dist: matplotlib>=3.10.1
Requires-Dist: memory-efficient-attention-pytorch>=0.1.6
Requires-Dist: pandas>=2.2.3
Requires-Dist: safetensors>=0.5.3
Requires-Dist: seaborn>=0.13.2
Requires-Dist: torch>=2.6.0
Requires-Dist: torchvision>=0.21.0
Requires-Dist: tqdm>=4.67.1
Requires-Dist: transformers>=4.52.4
Requires-Dist: wandb>=0.19.9
